[
  {
    "perfil": "ovidio-orellana",
    "aspecto": "Aspectos Profesionales",
    "puntaje": "5"
  },
  {
    "perfil": "ovidio-orellana",
    "aspecto": "Aspectos Académicos",
    "puntaje": "7"
  },
  {
    "perfil": "ovidio-orellana",
    "aspecto": "Cualidades Éticas y de Probidad",
    "puntaje": "8"
  },
  {
    "perfil": "ovidio-orellana",
    "aspecto": "Proyección Humana E Idoneidad",
    "puntaje": "5"
  },
  {
    "perfil": "luis-fernando-ruiz",
    "aspecto": "Aspectos Profesionales",
    "puntaje": "1"
  },
  {
    "perfil": "luis-fernando-ruiz",
    "aspecto": "Aspectos Académicos",
    "puntaje": "5"
  },
  {
    "perfil": "luis-fernando-ruiz",
    "aspecto": "Cualidades Éticas y de Probidad",
    "puntaje": "8"
  },
  {
    "perfil": "luis-fernando-ruiz",
    "aspecto": "Proyección Humana E Idoneidad",
    "puntaje": "10"
  },
  {
    "perfil": "alejandro-balsells",
    "aspecto": "Aspectos Profesionales",
    "puntaje": "8"
  },
  {
    "perfil": "alejandro-balsells",
    "aspecto": "Aspectos Académicos",
    "puntaje": "5"
  },
  {
    "perfil": "alejandro-balsells",
    "aspecto": "Cualidades Éticas y de Probidad",
    "puntaje": "9"
  },
  {
    "perfil": "alejandro-balsells",
    "aspecto": "Proyección Humana E Idoneidad",
    "puntaje": "7"
  },
  {
    "perfil": "joaquin-medina",
    "aspecto": "Aspectos Profesionales",
    "puntaje": "2"
  },
  {
    "perfil": "joaquin-medina",
    "aspecto": "Aspectos Académicos",
    "puntaje": "4"
  },
  {
    "perfil": "joaquin-medina",
    "aspecto": "Cualidades Éticas y de Probidad",
    "puntaje": "8"
  },
  {
    "perfil": "joaquin-medina",
    "aspecto": "Proyección Humana E Idoneidad",
    "puntaje": "3"
  }
]
